bioviz/__init__.py
bioviz/configs/__init__.py
bioviz/configs/base_cfg.py
bioviz/configs/distribution_cfg.py
bioviz/configs/line_cfg.py
bioviz/configs/oncoplot_annotations_cfg.py
bioviz/configs/oncoplot_cfg.py
bioviz/configs/table_cfg.py
bioviz/configs/volcano_cfg.py
bioviz/plots/__init__.py
bioviz/plots/distribution.py
bioviz/plots/grouped.py
bioviz/plots/lineplot.py
bioviz/plots/oncoplot.py
bioviz/plots/plot_composite_helpers.py
bioviz/plots/plot_helpers.py
bioviz/plots/table.py
bioviz/plots/volcano.py
bioviz/plots/waterfall.py
bioviz/utils/plot_utils.py
bioviz/utils/plotting.py
bioviz/utils/style.py
bioviz_kit-0.3.3.dist-info/licenses/LICENSE
bioviz_kit-0.3.3.dist-info/METADATA
bioviz_kit-0.3.3.dist-info/WHEEL
bioviz_kit-0.3.3.dist-info/top_level.txt
bioviz_kit-0.3.3.dist-info/RECORD
