Metadata-Version: 2.4
Name: bioviz-kit
Version: 0.3.3
Summary: Framework-agnostic plotting utilities for biological and clinical data visualization
Author-email: Victoria Cheung <victoriakcheung@gmail.com>
License: MIT License
Project-URL: Homepage, https://github.com/vic-cheung/bioviz-kit
Project-URL: Issue Tracker, https://github.com/vic-cheung/bioviz-kit/issues
Classifier: License :: OSI Approved :: MIT License
Classifier: Programming Language :: Python
Classifier: Programming Language :: Python :: 3
Classifier: Programming Language :: Python :: 3.11
Classifier: Topic :: Scientific/Engineering :: Visualization
Requires-Python: >=3.11
License-File: LICENSE
Requires-Dist: pandas>=2.0
Requires-Dist: matplotlib>=3.6
Requires-Dist: seaborn>=0.12
Requires-Dist: adjusttext>=0.8
Requires-Dist: loguru>=0.7
Requires-Dist: pydantic<3,>=1.10
Requires-Dist: ipykernel>=7.1.0
Requires-Dist: statsmodels>=0.14.6
Provides-Extra: testing
Requires-Dist: pytest; extra == "testing"
Dynamic: license-file
